nickname_gen/__init__.py
nickname_gen/convert.py
nickname_gen/data/EN/__init__.py
nickname_gen/data/EN/adjectives.json
nickname_gen/data/EN/adjectives.py
nickname_gen/data/EN/adjectives.txt
nickname_gen/data/EN/animals.json
nickname_gen/data/EN/animals.py
nickname_gen/data/EN/animals.txt
nickname_gen/data/EN/colors.json
nickname_gen/data/EN/colors.py
nickname_gen/data/EN/colors.txt
nickname_gen/data/RU/__init__.py
nickname_gen/data/RU/adjectives.json
nickname_gen/data/RU/adjectives.py
nickname_gen/data/RU/adjectives.txt
nickname_gen/data/RU/animals.json
nickname_gen/data/RU/animals.py
nickname_gen/data/RU/animals.txt
nickname_gen/data/RU/colors.json
nickname_gen/data/RU/colors.py
nickname_gen/data/RU/colors.txt
nickname_gen/exceptions.py
nickname_gen/generator.py
nickname_gen/words.py
nickname_gen/wtypes.py
nickname_gen-0.1.5.dist-info/LICENSE
nickname_gen-0.1.5.dist-info/METADATA
nickname_gen-0.1.5.dist-info/WHEEL
nickname_gen-0.1.5.dist-info/RECORD
