Metadata-Version: 2.1
Name: nickname-gen
Version: 0.1.5
Summary: Simple Python package for generate unique nikcname, e.g. Cool Crow, Purple Duck, Red Brave Tiger. It supports both English and Russian (including gender).
Home-page: https://github.com/L4zzur/nickname-gen
License: MIT
Author: L4zzur
Author-email: popovnikita01@gmail.com
Requires-Python: >=3.11,<4.0
Classifier: License :: OSI Approved :: MIT License
Classifier: Programming Language :: Python :: 3
Classifier: Programming Language :: Python :: 3.11
Classifier: Programming Language :: Python :: 3.12
Requires-Dist: pymorphy3 (>=2.0.1,<3.0.0)
Project-URL: Repository, https://github.com/L4zzur/nickname-gen
